edq/__init__.py
edq/py.typed
edq/cli/__init__.py
edq/cli/__main__.py
edq/cli/version.py
edq/cli/config/__init__.py
edq/cli/config/__main__.py
edq/cli/config/list.py
edq/cli/http/__init__.py
edq/cli/http/__main__.py
edq/cli/http/exchange-server.py
edq/cli/http/send-exchange.py
edq/cli/http/verify-exchanges.py
edq/cli/testing/__init__.py
edq/cli/testing/__main__.py
edq/cli/testing/cli-test.py
edq/core/__init__.py
edq/core/argparser.py
edq/core/argparser_test.py
edq/core/config.py
edq/core/config_test.py
edq/core/errors.py
edq/core/log.py
edq/core/version.py
edq/net/__init__.py
edq/net/cli.py
edq/net/exchange.py
edq/net/exchangeserver.py
edq/net/request.py
edq/net/request_test.py
edq/net/util.py
edq/procedure/__init__.py
edq/procedure/verify_exchanges.py
edq/testing/__init__.py
edq/testing/asserts.py
edq/testing/cli.py
edq/testing/cli_test.py
edq/testing/httpserver.py
edq/testing/httpserver_test.py
edq/testing/run.py
edq/testing/serverrunner.py
edq/testing/unittest.py
edq/testing/testdata/cli/data/configs/empty/edq-config.json
edq/testing/testdata/cli/data/configs/simple-1/edq-config.json
edq/testing/testdata/cli/data/configs/simple-2/edq-config.json
edq/testing/testdata/cli/data/configs/value-number/edq-config.json
edq/testing/testdata/cli/tests/help_base.txt
edq/testing/testdata/cli/tests/platform_skip.txt
edq/testing/testdata/cli/tests/version_base.txt
edq/testing/testdata/cli/tests/config/list/config_list_base.txt
edq/testing/testdata/cli/tests/config/list/config_list_config_value_number.txt
edq/testing/testdata/cli/tests/config/list/config_list_ignore_config.txt
edq/testing/testdata/cli/tests/config/list/config_list_no_config.txt
edq/testing/testdata/cli/tests/config/list/config_list_show_origin.txt
edq/testing/testdata/cli/tests/config/list/config_list_skip_header.txt
edq/testing/testdata/http/exchanges/simple.httpex.json
edq/testing/testdata/http/exchanges/simple_anchor.httpex.json
edq/testing/testdata/http/exchanges/simple_file.httpex.json
edq_utils-0.4.0.dist-info/licenses/LICENSE
edq_utils-0.4.0.dist-info/METADATA
edq_utils-0.4.0.dist-info/WHEEL
edq_utils-0.4.0.dist-info/top_level.txt
edq_utils-0.4.0.dist-info/RECORD
