Metadata-Version: 2.4
Name: edq-utils
Version: 0.4.0
Summary: Common utilities used by EduLinq Python projects.
Author-email: Eriq Augustine <eriq@edulinq.org>
License: MIT License
Project-URL: Homepage, https://github.com/edulinq/python-utils
Project-URL: Repository, https://github.com/edulinq/python-utils
Keywords: education,utilities
Classifier: Intended Audience :: Developers
Classifier: License :: OSI Approved :: MIT License
Classifier: Programming Language :: Python :: 3.9
Requires-Python: >=3.9
License-File: LICENSE
Requires-Dist: json5>=0.9.14
Requires-Dist: platformdirs
Requires-Dist: requests
Requires-Dist: requests-toolbelt
Provides-Extra: dev
Requires-Dist: mypy>=1.14.1; extra == "dev"
Requires-Dist: pdoc>=14.7.0; extra == "dev"
Requires-Dist: pylint; extra == "dev"
Requires-Dist: twine; extra == "dev"
Requires-Dist: vermin; extra == "dev"
Dynamic: license-file
